[
  {
    "id": "allgemein",
    "translationKey": "ALLGEMEIN"
  },
  {
    "id": "notfaelle",
    "translationKey": "NOTFAELLE"
  },
  {
    "id": "friedenscamp",
    "translationKey": "FRIEDENSCAMP"
  },
  {
    "id": "friedensfussballturnier",
    "translationKey": "FRIEDENSFUSSBALLTURNIER"
  },
  {
    "id": "antibasenkongress",
    "translationKey": "ANTIBASENKONGRESS"
  },
  {
    "id": "abendveranstaltung",
    "translationKey": "ABENDVERANSTALTUNG"
  },
  {
    "id": "demonstration",
    "translationKey": "DEMONSTRATION"
  }
]
